fake_read_write_files/LICENSE
fake_read_write_files/README.MD
fake_read_write_files/__init__.py
fake_read_write_files/requirements.txt
fake_read_write_files/thirdparty.json
fake_read_write_files-0.10.dist-info/LICENSE.rst
fake_read_write_files-0.10.dist-info/METADATA
fake_read_write_files-0.10.dist-info/WHEEL
fake_read_write_files-0.10.dist-info/top_level.txt
fake_read_write_files-0.10.dist-info/RECORD
